odoo/addons/calendar_public_holiday/README.rst
odoo/addons/calendar_public_holiday/__init__.py
odoo/addons/calendar_public_holiday/__manifest__.py
odoo/addons/calendar_public_holiday/hooks.py
odoo/addons/calendar_public_holiday/data/data.xml
odoo/addons/calendar_public_holiday/i18n/calendar_public_holiday.pot
odoo/addons/calendar_public_holiday/i18n/es.po
odoo/addons/calendar_public_holiday/i18n/it.po
odoo/addons/calendar_public_holiday/models/__init__.py
odoo/addons/calendar_public_holiday/models/calendar_public_holiday.py
odoo/addons/calendar_public_holiday/models/calendar_public_holiday_line.py
odoo/addons/calendar_public_holiday/readme/CONTRIBUTORS.md
odoo/addons/calendar_public_holiday/readme/CREDITS.md
odoo/addons/calendar_public_holiday/readme/DESCRIPTION.md
odoo/addons/calendar_public_holiday/readme/USAGE.md
odoo/addons/calendar_public_holiday/security/ir.model.access.csv
odoo/addons/calendar_public_holiday/static/description/icon.png
odoo/addons/calendar_public_holiday/static/description/index.html
odoo/addons/calendar_public_holiday/tests/__init__.py
odoo/addons/calendar_public_holiday/tests/test_calendar_public_holiday.py
odoo/addons/calendar_public_holiday/views/calendar_public_holiday_view.xml
odoo/addons/calendar_public_holiday/wizards/__init__.py
odoo/addons/calendar_public_holiday/wizards/calendar_public_holiday_next_year_wizard.py
odoo/addons/calendar_public_holiday/wizards/calendar_public_holiday_next_year_wizard.xml
odoo_addon_calendar_public_holiday-18.0.1.0.0.8.dist-info/METADATA
odoo_addon_calendar_public_holiday-18.0.1.0.0.8.dist-info/WHEEL
odoo_addon_calendar_public_holiday-18.0.1.0.0.8.dist-info/top_level.txt
odoo_addon_calendar_public_holiday-18.0.1.0.0.8.dist-info/RECORD
