Metadata-Version: 2.1
Name: odoo-addon-calendar_public_holiday
Version: 18.0.1.0.0.8
Requires-Python: >=3.10
Requires-Dist: odoo==18.0.*
Requires-Dist: openupgradelib
Summary: Manage Public Holidays
Home-page: https://github.com/OCA/calendar
License: AGPL-3
Author: Michael Telahun Makonnen, Tecnativa, Fekete Mihai (Forest and Biomass Services Romania), Druidoo, Odoo Community Association (OCA), Camptocamp,
Author-email: support@odoo-community.org
Classifier: Programming Language :: Python
Classifier: Framework :: Odoo
Classifier: Framework :: Odoo :: 18.0
Classifier: License :: OSI Approved :: GNU Affero General Public License v3
